goodway_configs/__init__.py
goodway_configs/config_loader/__init__.py
goodway_configs/config_loader/base.py
goodway_configs/config_loader/etcd_loader.py
goodway_configs/config_loader/json_loader.py
goodway_configs/config_loader/multi_loader.py
goodway_configs/config_loader/yaml_loader.py
goodway_configs-0.1.0.dist-info/LICENSE.md
goodway_configs-0.1.0.dist-info/METADATA
goodway_configs-0.1.0.dist-info/WHEEL
goodway_configs-0.1.0.dist-info/RECORD
